versiref/__init__.py
versiref/bible_ref.py
versiref/py.typed
versiref/ref_parser.py
versiref/ref_style.py
versiref/versification.py
versiref/data/book_names/en-cmos_long.json
versiref/data/book_names/en-cmos_short.json
versiref/data/book_names/en-sbl_abbreviations.json
versiref/data/book_names/en-sbl_names.json
versiref/data/book_names/it-cei_abbreviazioni.json
versiref/data/book_names/it-cei_nomi.json
versiref/data/versifications/eng.json
versiref/data/versifications/lxx.json
versiref/data/versifications/nabre.json
versiref/data/versifications/nova-vulgata.json
versiref/data/versifications/org.json
versiref/data/versifications/rsc.json
versiref/data/versifications/rso.json
versiref/data/versifications/vulgata.json
versiref-0.1.0.dist-info/METADATA
versiref-0.1.0.dist-info/WHEEL
versiref-0.1.0.dist-info/licenses/LICENSE
versiref-0.1.0.dist-info/RECORD
