Metadata-Version: 2.4
Name: versiref
Version: 0.1.0
Summary: A package for sophisticated parsing, manipulation, and printing of references to the Bible
Project-URL: Homepage, https://github.com/fiapps/versiref
Project-URL: Issues, https://github.com/fiapps/versiref/issues
Author-email: "Fr. John Lawrence M. Polis" <emptier-sank-dose@duck.com>
License-Expression: MIT
License-File: LICENSE
Classifier: Development Status :: 3 - Alpha
Classifier: Intended Audience :: Developers
Classifier: Intended Audience :: Religion
Classifier: Operating System :: OS Independent
Classifier: Programming Language :: Python :: 3
Classifier: Programming Language :: Python :: 3 :: Only
Classifier: Programming Language :: Python :: 3.9
Classifier: Programming Language :: Python :: 3.10
Classifier: Programming Language :: Python :: 3.11
Classifier: Programming Language :: Python :: 3.12
Classifier: Programming Language :: Python :: 3.13
Classifier: Topic :: Religion
Classifier: Topic :: Text Processing
Requires-Python: >=3.9
Requires-Dist: pyparsing>=3.2.3
